niuzepeng/__init__.py
niuzepeng/nzp.py
niuzepeng-1.0.2.dist-info/METADATA
niuzepeng-1.0.2.dist-info/RECORD
niuzepeng-1.0.2.dist-info/WHEEL
niuzepeng-1.0.2.dist-info/top_level.txt
