Metadata-Version: 2.1
Name: niuzepeng
Version: 1.0.2
Summary: This is my first create!
Home-page: https://github.com/zepen
Author: Niuzepeng
Author-email: 18217127859@163.com
License: MIT
Platform: UNKNOWN
